hardware/src/security_puf.v
module security_puf (
    input clk,
    input reset,
    input start,
    input [7:0] challenge,
    output reg [7:0] response,
    output reg done
);
    reg [7:0] lfsr;
    reg [3:0] cycle_count;

    always @(posedge clk or posedge reset) begin
        if (reset) begin
            lfsr <= 8'b0;
            done <= 0;
            cycle_count <= 0;
            response <= 8'b0;
        end else if (start && !done) begin
            if (cycle_count == 0) begin
                lfsr <= challenge ^ 8'hA5; // Hardware seed
            end else begin
                // LFSR Polynomial
                lfsr <= {lfsr[6:0], lfsr[7] ^ lfsr[5] ^ lfsr[4] ^ lfsr[3]};
            end

            cycle_count <= cycle_count + 1;

            // Processing delay simulation
            if (cycle_count >= 4) begin
                response <= lfsr;
                done <= 1;
            end
        end else if (!start) begin
            done <= 0;
            cycle_count <= 0;
        end
    end
endmodule

waveform.vcd
$version Generated by VerilatedVcd $end
$date Thu May  7 07:08:39 2026
 $end
$timescale   1ps $end

 $scope module TOP $end
  $var wire  8 & challenge [7:0] $end
  $var wire  1 # clk $end
  $var wire  1 ( done $end
  $var wire  1 $ reset $end
  $var wire  8 ' response [7:0] $end
  $var wire  1 % start $end
  $scope module security_puf $end
   $var wire  8 & challenge [7:0] $end
   $var wire  1 # clk $end
   $var wire  4 * cycle_count [3:0] $end
   $var wire  1 ( done $end
   $var wire  8 ) lfsr [7:0] $end
   $var wire  1 $ reset $end
   $var wire  8 ' response [7:0] $end
   $var wire  1 % start $end
  $upscope $end
 $upscope $end
$enddefinitions $end


#0
1#
1$
0%
b00000000 &
b00000000 '
0(
b00000000 )
b0000 *
#1
0#
#2
1#
0$
1%
b11101001 &
b01001100 )
b0001 *
#3
0#
#4
1#
b10011001 )
b0010 *
#5
0#
#6
1#
b00110011 )
b0011 *
#7
0#
#8
1#
b01100110 )
b0100 *
#9
0#
#10
1#
b01100110 '
1(
b11001101 )
b0101 *
#11
0#
#12
1#
0%
0(
b0000 *
#13
0#
#14
1#
1%
b00011010 &
b10111111 )
b0001 *
#15
0#
#16
1#
b01111110 )
b0010 *
#17
0#
#18
1#
b11111101 )
b0011 *
#19
0#
#20
1#
b11111010 )
b0100 *
#21
0#
#22
1#
b11111010 '
1(
b11110100 )
b0101 *
#23
0#
#24
1#
0%
0(
b0000 *
#25
0#
#26
1#
1%
b11100010 &
b01000111 )
b0001 *
#27
0#
#28
1#
b10001110 )
b0010 *
#29
0#
#30
1#
b00011100 )
b0011 *
#31
0#
#32
1#
b00111000 )
b0100 *
#33
0#
#34
1#
b00111000 '
1(
b01110001 )
b0101 *
#35
0#
#36
1#
0%
0(
b0000 *
#37
0#
#38
1#
1%
b10101101 &
b00001000 )
b0001 *
#39
0#
#40
1#
b00010001 )
b0010 *
#41
0#
#42
1#
b00100011 )
b0011 *
#43
0#
#44
1#
b01000111 )
b0100 *
#45
0#
#46
1#
b01000111 '
1(
b10001110 )
b0101 *
#47
0#
#48
1#
0%
0(
b0000 *
#49
0#
#50
1#
1%
b00110111 &
b10010010 )
b0001 *
#51
0#
#52
1#
b00100100 )
b0010 *
#53
0#
#54
1#
b01001001 )
b0011 *
#55
0#
#56
1#
b10010011 )
b0100 *
#57
0#
#58
1#
b10010011 '
1(
b00100110 )
b0101 *
#59
0#
#60
1#
0%
0(
b0000 *
#61
0#
#62
1#
1%
b11111011 &
b01011110 )
b0001 *
#63
0#
#64
1#
b10111100 )
b0010 *
#65
0#
#66
1#
b01111000 )
b0011 *
#67
0#
#68
1#
b11110001 )
b0100 *
#69
0#
#70
1#
b11110001 '
1(
b11100011 )
b0101 *
#71
0#
#72
1#
0%
0(
b0000 *
#73
0#
#74
1#
1%
b11000011 &
b01100110 )
b0001 *
#75
0#
#76
1#
b11001101 )
b0010 *
#77
0#
#78
1#
b10011010 )
b0011 *
#79
0#
#80
1#
b00110101 )
b0100 *
#81
0#
#82
1#
b00110101 '
1(
b01101010 )
b0101 *
#83
0#
#84
1#
0%
0(
b0000 *
#85
0#
#86
1#
1%
b11010101 &
b01110000 )
b0001 *
#87
0#
#88
1#
b11100000 )
b0010 *
#89
0#
#90
1#
b11000000 )
b0011 *
#91
0#
#92
1#
b10000001 )
b0100 *
#93
0#
#94
1#
b10000001 '
1(
b00000011 )
b0101 *
#95
0#
#96
1#
0%
0(
b0000 *
#97
0#
#98
1#
1%
b01100110 &
b11000011 )
b0001 *
#99
0#
#100
1#
b10000111 )
b0010 *
#101
0#
#102
1#
b00001111 )
b0011 *
#103
0#
#104
1#
b00011111 )
b0100 *
#105
0#
#106
1#
b00011111 '
1(
b00111110 )
b0101 *
#107
0#
#108
1#
0%
0(
b0000 *
#109
0#
#110
1#
1%
b10010010 &
b00110111 )
b0001 *
#111
0#
#112
1#
b01101110 )
b0010 *
#113
0#
#114
1#
b11011100 )
b0011 *
#115
0#
#116
1#
b10111001 )
b0100 *
#117
0#
#118
1#
b10111001 '
1(
b01110010 )
b0101 *
#119
0#
#120
1#
0%
0(
b0000 *
#121
0#
#122
1#
1%
b11011111 &
b01111010 )
b0001 *
#123
0#
#124
1#
b11110101 )
b0010 *
#125
0#
#126
1#
b11101011 )
b0011 *
#127
0#
#128
1#
b11010111 )
b0100 *
#129
0#
#130
1#
b11010111 '
1(
b10101110 )
b0101 *
#131
0#
#132
1#
0%
0(
b0000 *
#133
0#
#134
1#
1%
b00111010 &
b10011111 )
b0001 *
#135
0#
#136
1#
b00111111 )
b0010 *
#137
0#
#138
1#
b01111111 )
b0011 *
#139
0#
#140
1#
b11111111 )
b0100 *
#141
0#
#142
1#
b11111111 '
1(
b11111110 )
b0101 *
#143
0#
#144
1#
0%
0(
b0000 *
#145
0#
#146
1#
1%
b11011100 &
b01111001 )
b0001 *
#147
0#
#148
1#
b11110011 )
b0010 *
#149
0#
#150
1#
b11100111 )
b0011 *
#151
0#
#152
1#
b11001110 )
b0100 *
#153
0#
#154
1#
b11001110 '
1(
b10011100 )
b0101 *
#155
0#
#156
1#
0%
0(
b0000 *
#157
0#
#158
1#
1%
b11001101 &
b01101000 )
b0001 *
#159
0#
#160
1#
b11010000 )
b0010 *
#161
0#
#162
1#
b10100000 )
b0011 *
#163
0#
#164
1#
b01000000 )
b0100 *
#165
0#
#166
1#
b01000000 '
1(
b10000000 )
b0101 *
#167
0#
#168
1#
0%
0(
b0000 *
#169
0#
#170
1#
1%
b01000110 &
b11100011 )
b0001 *
#171
0#
#172
1#
b11000110 )
b0010 *
#173
0#
#174
1#
b10001101 )
b0011 *
#175
0#
#176
1#
b00011010 )
b0100 *
#177
0#
#178
1#
b00011010 '
1(
b00110100 )
b0101 *
#179
0#
#180
1#
0%
0(
b0000 *
#181
0#
#182
1#
1%
b11001100 &
b01101001 )
b0001 *
#183
0#
#184
1#
b11010010 )
b0010 *
#185
0#
#186
1#
b10100100 )
b0011 *
#187
0#
#188
1#
b01001000 )
b0100 *
#189
0#
#190
1#
b01001000 '
1(
b10010001 )
b0101 *
#191
0#
#192
1#
0%
0(
b0000 *
#193
0#
#194
1#
1%
b10110001 &
b00010100 )
b0001 *
#195
0#
#196
1#
b00101001 )
b0010 *
#197
0#
#198
1#
b01010010 )
b0011 *
#199
0#
#200
1#
b10100101 )
b0100 *
#201
0#
#202
1#
b10100101 '
1(
b01001010 )
b0101 *
#203
0#
#204
1#
0%
0(
b0000 *
#205
0#
#206
1#
1%
b11101000 &
b01001101 )
b0001 *
#207
0#
#208
1#
b10011011 )
b0010 *
#209
0#
#210
1#
b00110111 )
b0011 *
#211
0#
#212
1#
b01101110 )
b0100 *
#213
0#
#214
1#
b01101110 '
1(
b11011100 )
b0101 *
#215
0#
#216
1#
0%
0(
b0000 *
#217
0#
#218
1#
1%
b01011001 &
b11111100 )
b0001 *
#219
0#
#220
1#
b11111000 )
b0010 *
#221
0#
#222
1#
b11110000 )
b0011 *
#223
0#
#224
1#
b11100001 )
b0100 *
#225
0#
#226
1#
b11100001 '
1(
b11000010 )
b0101 *
#227
0#
#228
1#
0%
0(
b0000 *
#229
0#
#230
1#
1%
b01000111 &
b11100010 )
b0001 *
#231
0#
#232
1#
b11000100 )
b0010 *
#233
0#
#234
1#
b10001001 )
b0011 *
#235
0#
#236
1#
b00010010 )
b0100 *
#237
0#
#238
1#
b00010010 '
1(
b00100101 )
b0101 *
#239
0#
#240
1#
0%
0(
b0000 *
#241
0#
#242
1#
1%
b11010101 &
b01110000 )
b0001 *
#243
0#
#244
1#
b11100000 )
b0010 *
#245
0#
#246
1#
b11000000 )
b0011 *
#247
0#
#248
1#
b10000001 )
b0100 *
#249
0#
#250
1#
b10000001 '
1(
b00000011 )
b0101 *
#251
0#
#252
1#
0%
0(
b0000 *
#253
0#
#254
1#
1%
b10011011 &
b00111110 )
b0001 *
#255
0#
#256
1#
b01111101 )
b0010 *
#257
0#
#258
1#
b11111011 )
b0011 *
#259
0#
#260
1#
b11110110 )
b0100 *
#261
0#
#262
1#
b11110110 '
1(
b11101101 )
b0101 *
#263
0#
#264
1#
0%
0(
b0000 *
#265
0#
#266
1#
1%
b01000001 &
b11100100 )
b0001 *
#267
0#
#268
1#
b11001000 )
b0010 *
#269
0#
#270
1#
b10010000 )
b0011 *
#271
0#
#272
1#
b00100000 )
b0100 *
#273
0#
#274
1#
b00100000 '
1(
b01000001 )
b0101 *
#275
0#
#276
1#
0%
0(
b0000 *
#277
0#
#278
1#
1%
b00111000 &
b10011101 )
b0001 *
#279
0#
#280
1#
b00111011 )
b0010 *
#281
0#
#282
1#
b01110111 )
b0011 *
#283
0#
#284
1#
b11101110 )
b0100 *
#285
0#
#286
1#
b11101110 '
1(
b11011101 )
b0101 *
#287
0#
#288
1#
0%
0(
b0000 *
#289
0#
#290
1#
1%
b11001001 &
b01101100 )
b0001 *
#291
0#
#292
1#
b11011000 )
b0010 *
#293
0#
#294
1#
b10110001 )
b0011 *
#295
0#
#296
1#
b01100011 )
b0100 *
#297
0#
#298
1#
b01100011 '
1(
b11000111 )
b0101 *
#299
0#
#300
1#
0%
0(
b0000 *
#301
0#
#302
1#
1%
b11011001 &
b01111100 )
b0001 *
#303
0#
#304
1#
b11111001 )
b0010 *
#305
0#
#306
1#
b11110010 )
b0011 *
#307
0#
#308
1#
b11100101 )
b0100 *
#309
0#
#310
1#
b11100101 '
1(
b11001010 )
b0101 *
#311
0#
#312
1#
0%
0(
b0000 *
#313
0#
#314
1#
1%
b11010011 &
b01110110 )
b0001 *
#315
0#
#316
1#
b11101100 )
b0010 *
#317
0#
#318
1#
b11011001 )
b0011 *
#319
0#
#320
1#
b10110011 )
b0100 *
#321
0#
#322
1#
b10110011 '
1(
b01100111 )
b0101 *
#323
0#
#324
1#
0%
0(
b0000 *
#325
0#
#326
1#
1%
b00000111 &
b10100010 )
b0001 *
#327
0#
#328
1#
b01000100 )
b0010 *
#329
0#
#330
1#
b10001000 )
b0011 *
#331
0#
#332
1#
b00010000 )
b0100 *
#333
0#
#334
1#
b00010000 '
1(
b00100001 )
b0101 *
#335
0#
#336
1#
0%
0(
b0000 *
#337
0#
#338
1#
1%
b11101111 &
b01001010 )
b0001 *
#339
0#
#340
1#
b10010101 )
b0010 *
#341
0#
#342
1#
b00101010 )
b0011 *
#343
0#
#344
1#
b01010100 )
b0100 *
#345
0#
#346
1#
b01010100 '
1(
b10101001 )
b0101 *
#347
0#
#348
1#
0%
0(
b0000 *
#349
0#
#350
1#
1%
b11000010 &
b01100111 )
b0001 *
#351
0#
#352
1#
b11001111 )
b0010 *
#353
0#
#354
1#
b10011110 )
b0011 *
#355
0#
#356
1#
b00111101 )
b0100 *
#357
0#
#358
1#
b00111101 '
1(
b01111011 )
b0101 *
#359
0#
#360
1#
0%
0(
b0000 *
#361
0#
#362
1#
1%
b11011101 &
b01111000 )
b0001 *
#363
0#
#364
1#
b11110001 )
b0010 *
#365
0#
#366
1#
b11100011 )
b0011 *
#367
0#
#368
1#
b11000110 )
b0100 *
#369
0#
#370
1#
b11000110 '
1(
b10001101 )
b0101 *
#371
0#
#372
1#
0%
0(
b0000 *
#373
0#
#374
1#
1%
b01110111 &
b11010010 )
b0001 *
#375
0#
#376
1#
b10100100 )
b0010 *
#377
0#
#378
1#
b01001000 )
b0011 *
#379
0#
#380
1#
b10010001 )
b0100 *
#381
0#
#382
1#
b10010001 '
1(
b00100010 )
b0101 *
#383
0#
#384
1#
0%
0(
b0000 *
#385
0#
#386
1#
1%
b00010100 &
b10110001 )
b0001 *
#387
0#
#388
1#
b01100011 )
b0010 *
#389
0#
#390
1#
b11000111 )
b0011 *
#391
0#
#392
1#
b10001111 )
b0100 *
#393
0#
#394
1#
b10001111 '
1(
b00011110 )
b0101 *
#395
0#
#396
1#
0%
0(
b0000 *
#397
0#
#398
1#
1%
b01111011 &
b11011110 )
b0001 *
#399
0#
#400
1#
b10111101 )
b0010 *
#401
0#
#402
1#
b01111010 )
b0011 *
#403
0#
#404
1#
b11110101 )
b0100 *
#405
0#
#406
1#
b11110101 '
1(
b11101011 )
b0101 *
#407
0#
#408
1#
0%
0(
b0000 *
#409
0#
#410
1#
1%
b11001011 &
b01101110 )
b0001 *
#411
0#
#412
1#
b11011100 )
b0010 *
#413
0#
#414
1#
b10111001 )
b0011 *
#415
0#
#416
1#
b01110010 )
b0100 *
#417
0#
#418
1#
b01110010 '
1(
b11100100 )
b0101 *
#419
0#
#420
1#
0%
0(
b0000 *
#421
0#
#422
1#
1%
b11011000 &
b01111101 )
b0001 *
#423
0#
#424
1#
b11111011 )
b0010 *
#425
0#
#426
1#
b11110110 )
b0011 *
#427
0#
#428
1#
b11101101 )
b0100 *
#429
0#
#430
1#
b11101101 '
1(
b11011011 )
b0101 *
#431
0#
#432
1#
0%
0(
b0000 *
#433
0#
#434
1#
1%
b11010011 &
b01110110 )
b0001 *
#435
0#
#436
1#
b11101100 )
b0010 *
#437
0#
#438
1#
b11011001 )
b0011 *
#439
0#
#440
1#
b10110011 )
b0100 *
#441
0#
#442
1#
b10110011 '
1(
b01100111 )
b0101 *
#443
0#
#444
1#
0%
0(
b0000 *
#445
0#
#446
1#
1%
b01011000 &
b11111101 )
b0001 *
#447
0#
#448
1#
b11111010 )
b0010 *
#449
0#
#450
1#
b11110100 )
b0011 *
#451
0#
#452
1#
b11101001 )
b0100 *
#453
0#
#454
1#
b11101001 '
1(
b11010011 )
b0101 *
#455
0#
#456
1#
0%
0(
b0000 *
#457
0#
#458
1#
1%
b01011001 &
b11111100 )
b0001 *
#459
0#
#460
1#
b11111000 )
b0010 *
#461
0#
#462
1#
b11110000 )
b0011 *
#463
0#
#464
1#
b11100001 )
b0100 *
#465
0#
#466
1#
b11100001 '
1(
b11000010 )
b0101 *
#467
0#
#468
1#
0%
0(
b0000 *
#469
0#
#470
1#
1%
b10100111 &
b00000010 )
b0001 *
#471
0#
#472
1#
b00000100 )
b0010 *
#473
0#
#474
1#
b00001000 )
b0011 *
#475
0#
#476
1#
b00010001 )
b0100 *
#477
0#
#478
1#
b00010001 '
1(
b00100011 )
b0101 *
#479
0#
#480
1#
0%
0(
b0000 *
#481
0#
#482
1#
1%
b01101011 &
b11001110 )
b0001 *
#483
0#
#484
1#
b10011100 )
b0010 *
#485
0#
#486
1#
b00111001 )
b0011 *
#487
0#
#488
1#
b01110011 )
b0100 *
#489
0#
#490
1#
b01110011 '
1(
b11100110 )
b0101 *
#491
0#
#492
1#
0%
0(
b0000 *
#493
0#
#494
1#
1%
b01110110 &
b11010011 )
b0001 *
#495
0#
#496
1#
b10100110 )
b0010 *
#497
0#
#498
1#
b01001100 )
b0011 *
#499
0#
#500
1#
b10011001 )
b0100 *
#501
0#
#502
1#
b10011001 '
1(
b00110011 )
b0101 *
#503
0#
#504
1#
0%
0(
b0000 *
#505
0#
#506
1#
1%
b00011000 &
b10111101 )
b0001 *
#507
0#
#508
1#
b01111010 )
b0010 *
#509
0#
#510
1#
b11110101 )
b0011 *
#511
0#
#512
1#
b11101011 )
b0100 *
#513
0#
#514
1#
b11101011 '
1(
b11010111 )
b0101 *
#515
0#
#516
1#
0%
0(
b0000 *
#517
0#
#518
1#
1%
b11001111 &
b01101010 )
b0001 *
#519
0#
#520
1#
b11010100 )
b0010 *
#521
0#
#522
1#
b10101000 )
b0011 *
#523
0#
#524
1#
b01010001 )
b0100 *
#525
0#
#526
1#
b01010001 '
1(
b10100011 )
b0101 *
#527
0#
#528
1#
0%
0(
b0000 *
#529
0#
#530
1#
1%
b11011010 &
b01111111 )
b0001 *
#531
0#
#532
1#
b11111111 )
b0010 *
#533
0#
#534
1#
b11111110 )
b0011 *
#535
0#
#536
1#
b11111100 )
b0100 *
#537
0#
#538
1#
b11111100 '
1(
b11111000 )
b0101 *
#539
0#
#540
1#
0%
0(
b0000 *
#541
0#
#542
1#
1%
b11101001 &
b01001100 )
b0001 *
#543
0#
#544
1#
b10011001 )
b0010 *
#545
0#
#546
1#
b00110011 )
b0011 *
#547
0#
#548
1#
b01100110 )
b0100 *
#549
0#
#550
1#
b01100110 '
1(
b11001101 )
b0101 *
#551
0#
#552
1#
0%
0(
b0000 *
#553
0#
#554
1#
1%
b01110000 &
b11010101 )
b0001 *
#555
0#
#556
1#
b10101010 )
b0010 *
#557
0#
#558
1#
b01010101 )
b0011 *
#559
0#
#560
1#
b10101011 )
b0100 *
#561
0#
#562
1#
b10101011 '
1(
b01010111 )
b0101 *
#563
0#
#564
1#
0%
0(
b0000 *
#565
0#
#566
1#
1%
b11000110 &
b01100011 )
b0001 *
#567
0#
#568
1#
b11000111 )
b0010 *
#569
0#
#570
1#
b10001111 )
b0011 *
#571
0#
#572
1#
b00011110 )
b0100 *
#573
0#
#574
1#
b00011110 '
1(
b00111100 )
b0101 *
#575
0#
#576
1#
0%
0(
b0000 *
#577
0#
#578
1#
1%
b11111110 &
b01011011 )
b0001 *
#579
0#
#580
1#
b10110110 )
b0010 *
#581
0#
#582
1#
b01101101 )
b0011 *
#583
0#
#584
1#
b11011010 )
b0100 *
#585
0#
#586
1#
b11011010 '
1(
b10110101 )
b0101 *
#587
0#
#588
1#
0%
0(
b0000 *
#589
0#
#590
1#
1%
b10101000 &
b00001101 )
b0001 *
#591
0#
#592
1#
b00011011 )
b0010 *
#593
0#
#594
1#
b00110110 )
b0011 *
#595
0#
#596
1#
b01101100 )
b0100 *
#597
0#
#598
1#
b01101100 '
1(
b11011000 )
b0101 *
#599
0#
#600
1#
0%
0(
b0000 *
#601
0#
#602
1#
1%
b00101000 &
b10001101 )
b0001 *
#603
0#
#604
1#
b00011010 )
b0010 *
#605
0#
#606
1#
b00110100 )
b0011 *
#607
0#
#608
1#
b01101000 )
b0100 *
#609
0#
#610
1#
b01101000 '
1(
b11010000 )
b0101 *
#611
0#
#612
1#
0%
0(
b0000 *
#613
0#
#614
1#
1%
b10001000 &
b00101101 )
b0001 *
#615
0#
#616
1#
b01011010 )
b0010 *
#617
0#
#618
1#
b10110100 )
b0011 *
#619
0#
#620
1#
b01101001 )
b0100 *
#621
0#
#622
1#
b01101001 '
1(
b11010010 )
b0101 *
#623
0#
#624
1#
0%
0(
b0000 *
#625
0#
#626
1#
1%
b10110110 &
b00010011 )
b0001 *
#627
0#
#628
1#
b00100111 )
b0010 *
#629
0#
#630
1#
b01001111 )
b0011 *
#631
0#
#632
1#
b10011111 )
b0100 *
#633
0#
#634
1#
b10011111 '
1(
b00111111 )
b0101 *
#635
0#
#636
1#
0%
0(
b0000 *
#637
0#
#638
1#
1%
b00100111 &
b10000010 )
b0001 *
#639
0#
#640
1#
b00000101 )
b0010 *
#641
0#
#642
1#
b00001010 )
b0011 *
#643
0#
#644
1#
b00010101 )
b0100 *
#645
0#
#646
1#
b00010101 '
1(
b00101011 )
b0101 *
#647
0#
#648
1#
0%
0(
b0000 *
#649
0#
#650
1#
1%
b01011001 &
b11111100 )
b0001 *
#651
0#
#652
1#
b11111000 )
b0010 *
#653
0#
#654
1#
b11110000 )
b0011 *
#655
0#
#656
1#
b11100001 )
b0100 *
#657
0#
#658
1#
b11100001 '
1(
b11000010 )
b0101 *
#659
0#
#660
1#
0%
0(
b0000 *
#661
0#
#662
1#
1%
b01110001 &
b11010100 )
b0001 *
#663
0#
#664
1#
b10101000 )
b0010 *
#665
0#
#666
1#
b01010001 )
b0011 *
#667
0#
#668
1#
b10100011 )
b0100 *
#669
0#
#670
1#
b10100011 '
1(
b01000110 )
b0101 *
#671
0#
#672
1#
0%
0(
b0000 *
#673
0#
#674
1#
1%
b01011011 &
b11111110 )
b0001 *
#675
0#
#676
1#
b11111100 )
b0010 *
#677
0#
#678
1#
b11111000 )
b0011 *
#679
0#
#680
1#
b11110000 )
b0100 *
#681
0#
#682
1#
b11110000 '
1(
b11100001 )
b0101 *
#683
0#
#684
1#
0%
0(
b0000 *
#685
0#
#686
1#
1%
b10100011 &
b00000110 )
b0001 *
#687
0#
#688
1#
b00001100 )
b0010 *
#689
0#
#690
1#
b00011001 )
b0011 *
#691
0#
#692
1#
b00110010 )
b0100 *
#693
0#
#694
1#
b00110010 '
1(
b01100100 )
b0101 *
#695
0#
#696
1#
0%
0(
b0000 *
#697
0#
#698
1#
1%
b10111110 &
b00011011 )
b0001 *
#699
0#
#700
1#
b00110110 )
b0010 *
#701
0#
#702
1#
b01101100 )
b0011 *
#703
0#
#704
1#
b11011000 )
b0100 *
#705
0#
#706
1#
b11011000 '
1(
b10110001 )
b0101 *
#707
0#
#708
1#
0%
0(
b0000 *
#709
0#
#710
1#
1%
b00111000 &
b10011101 )
b0001 *
#711
0#
#712
1#
b00111011 )
b0010 *
#713
0#
#714
1#
b01110111 )
b0011 *
#715
0#
#716
1#
b11101110 )
b0100 *
#717
0#
#718
1#
b11101110 '
1(
b11011101 )
b0101 *
#719
0#
#720
1#
0%
0(
b0000 *
#721
0#
#722
1#
1%
b00111001 &
b10011100 )
b0001 *
#723
0#
#724
1#
b00111001 )
b0010 *
#725
0#
#726
1#
b01110011 )
b0011 *
#727
0#
#728
1#
b11100110 )
b0100 *
#729
0#
#730
1#
b11100110 '
1(
b11001100 )
b0101 *
#731
0#
#732
1#
0%
0(
b0000 *
#733
0#
#734
1#
1%
b10001010 &
b00101111 )
b0001 *
#735
0#
#736
1#
b01011110 )
b0010 *
#737
0#
#738
1#
b10111100 )
b0011 *
#739
0#
#740
1#
b01111000 )
b0100 *
#741
0#
#742
1#
b01111000 '
1(
b11110001 )
b0101 *
#743
0#
#744
1#
0%
0(
b0000 *
#745
0#
#746
1#
1%
b10101110 &
b00001011 )
b0001 *
#747
0#
#748
1#
b00010111 )
b0010 *
#749
0#
#750
1#
b00101111 )
b0011 *
#751
0#
#752
1#
b01011110 )
b0100 *
#753
0#
#754
1#
b01011110 '
1(
b10111100 )
b0101 *
#755
0#
#756
1#
0%
0(
b0000 *
#757
0#
#758
1#
1%
b10111111 &
b00011010 )
b0001 *
#759
0#
#760
1#
b00110100 )
b0010 *
#761
0#
#762
1#
b01101000 )
b0011 *
#763
0#
#764
1#
b11010000 )
b0100 *
#765
0#
#766
1#
b11010000 '
1(
b10100000 )
b0101 *
#767
0#
#768
1#
0%
0(
b0000 *
#769
0#
#770
1#
1%
b10010101 &
b00110000 )
b0001 *
#771
0#
#772
1#
b01100000 )
b0010 *
#773
0#
#774
1#
b11000001 )
b0011 *
#775
0#
#776
1#
b10000011 )
b0100 *
#777
0#
#778
1#
b10000011 '
1(
b00000111 )
b0101 *
#779
0#
#780
1#
0%
0(
b0000 *
#781
0#
#782
1#
1%
b11011101 &
b01111000 )
b0001 *
#783
0#
#784
1#
b11110001 )
b0010 *
#785
0#
#786
1#
b11100011 )
b0011 *
#787
0#
#788
1#
b11000110 )
b0100 *
#789
0#
#790
1#
b11000110 '
1(
b10001101 )
b0101 *
#791
0#
#792
1#
0%
0(
b0000 *
#793
0#
#794
1#
1%
b11101010 &
b01001111 )
b0001 *
#795
0#
#796
1#
b10011111 )
b0010 *
#797
0#
#798
1#
b00111111 )
b0011 *
#799
0#
#800
1#
b01111111 )
b0100 *
#801
0#
#802
1#
b01111111 '
1(
b11111111 )
b0101 *
#803
0#
#804
1#
0%
0(
b0000 *
#805
0#
#806
1#
1%
b01000111 &
b11100010 )
b0001 *
#807
0#
#808
1#
b11000100 )
b0010 *
#809
0#
#810
1#
b10001001 )
b0011 *
#811
0#
#812
1#
b00010010 )
b0100 *
#813
0#
#814
1#
b00010010 '
1(
b00100101 )
b0101 *
#815
0#
#816
1#
0%
0(
b0000 *
#817
0#
#818
1#
1%
b11101010 &
b01001111 )
b0001 *
#819
0#
#820
1#
b10011111 )
b0010 *
#821
0#
#822
1#
b00111111 )
b0011 *
#823
0#
#824
1#
b01111111 )
b0100 *
#825
0#
#826
1#
b01111111 '
1(
b11111111 )
b0101 *
#827
0#
#828
1#
0%
0(
b0000 *
#829
0#
#830
1#
1%
b00010011 &
b10110110 )
b0001 *
#831
0#
#832
1#
b01101101 )
b0010 *
#833
0#
#834
1#
b11011010 )
b0011 *
#835
0#
#836
1#
b10110101 )
b0100 *
#837
0#
#838
1#
b10110101 '
1(
b01101011 )
b0101 *
#839
0#
#840
1#
0%
0(
b0000 *
#841
0#
#842
1#
1%
b01110011 &
b11010110 )
b0001 *
#843
0#
#844
1#
b10101100 )
b0010 *
#845
0#
#846
1#
b01011001 )
b0011 *
#847
0#
#848
1#
b10110010 )
b0100 *
#849
0#
#850
1#
b10110010 '
1(
b01100101 )
b0101 *
#851
0#
#852
1#
0%
0(
b0000 *
#853
0#
#854
1#
1%
b00101000 &
b10001101 )
b0001 *
#855
0#
#856
1#
b00011010 )
b0010 *
#857
0#
#858
1#
b00110100 )
b0011 *
#859
0#
#860
1#
b01101000 )
b0100 *
#861
0#
#862
1#
b01101000 '
1(
b11010000 )
b0101 *
#863
0#
#864
1#
0%
0(
b0000 *
#865
0#
#866
1#
1%
b01111111 &
b11011010 )
b0001 *
#867
0#
#868
1#
b10110101 )
b0010 *
#869
0#
#870
1#
b01101011 )
b0011 *
#871
0#
#872
1#
b11010110 )
b0100 *
#873
0#
#874
1#
b11010110 '
1(
b10101100 )
b0101 *
#875
0#
#876
1#
0%
0(
b0000 *
#877
0#
#878
1#
1%
b10010011 &
b00110110 )
b0001 *
#879
0#
#880
1#
b01101100 )
b0010 *
#881
0#
#882
1#
b11011000 )
b0011 *
#883
0#
#884
1#
b10110001 )
b0100 *
#885
0#
#886
1#
b10110001 '
1(
b01100011 )
b0101 *
#887
0#
#888
1#
0%
0(
b0000 *
#889
0#
#890
1#
1%
b11001000 &
b01101101 )
b0001 *
#891
0#
#892
1#
b11011010 )
b0010 *
#893
0#
#894
1#
b10110101 )
b0011 *
#895
0#
#896
1#
b01101011 )
b0100 *
#897
0#
#898
1#
b01101011 '
1(
b11010110 )
b0101 *
#899
0#
#900
1#
0%
0(
b0000 *
#901
0#
#902
1#
1%
b10001101 &
b00101000 )
b0001 *
#903
0#
#904
1#
b01010000 )
b0010 *
#905
0#
#906
1#
b10100001 )
b0011 *
#907
0#
#908
1#
b01000010 )
b0100 *
#909
0#
#910
1#
b01000010 '
1(
b10000100 )
b0101 *
#911
0#
#912
1#
0%
0(
b0000 *
#913
0#
#914
1#
1%
b01001011 &
b11101110 )
b0001 *
#915
0#
#916
1#
b11011101 )
b0010 *
#917
0#
#918
1#
b10111011 )
b0011 *
#919
0#
#920
1#
b01110110 )
b0100 *
#921
0#
#922
1#
b01110110 '
1(
b11101100 )
b0101 *
#923
0#
#924
1#
0%
0(
b0000 *
#925
0#
#926
1#
1%
b11110010 &
b01010111 )
b0001 *
#927
0#
#928
1#
b10101111 )
b0010 *
#929
0#
#930
1#
b01011111 )
b0011 *
#931
0#
#932
1#
b10111110 )
b0100 *
#933
0#
#934
1#
b10111110 '
1(
b01111100 )
b0101 *
#935
0#
#936
1#
0%
0(
b0000 *
#937
0#
#938
1#
1%
b00011011 &
b10111110 )
b0001 *
#939
0#
#940
1#
b01111100 )
b0010 *
#941
0#
#942
1#
b11111001 )
b0011 *
#943
0#
#944
1#
b11110010 )
b0100 *
#945
0#
#946
1#
b11110010 '
1(
b11100101 )
b0101 *
#947
0#
#948
1#
0%
0(
b0000 *
#949
0#
#950
1#
1%
b11011010 &
b01111111 )
b0001 *
#951
0#
#952
1#
b11111111 )
b0010 *
#953
0#
#954
1#
b11111110 )
b0011 *
#955
0#
#956
1#
b11111100 )
b0100 *
#957
0#
#958
1#
b11111100 '
1(
b11111000 )
b0101 *
#959
0#
#960
1#
0%
0(
b0000 *
#961
0#
#962
1#
1%
b01001110 &
b11101011 )
b0001 *
#963
0#
#964
1#
b11010111 )
b0010 *
#965
0#
#966
1#
b10101110 )
b0011 *
#967
0#
#968
1#
b01011101 )
b0100 *
#969
0#
#970
1#
b01011101 '
1(
b10111010 )
b0101 *
#971
0#
#972
1#
0%
0(
b0000 *
#973
0#
#974
1#
1%
b11010110 &
b01110011 )
b0001 *
#975
0#
#976
1#
b11100110 )
b0010 *
#977
0#
#978
1#
b11001100 )
b0011 *
#979
0#
#980
1#
b10011000 )
b0100 *
#981
0#
#982
1#
b10011000 '
1(
b00110001 )
b0101 *
#983
0#
#984
1#
0%
0(
b0000 *
#985
0#
#986
1#
1%
b00010011 &
b10110110 )
b0001 *
#987
0#
#988
1#
b01101101 )
b0010 *
#989
0#
#990
1#
b11011010 )
b0011 *
#991
0#
#992
1#
b10110101 )
b0100 *
#993
0#
#994
1#
b10110101 '
1(
b01101011 )
b0101 *
#995
0#
#996
1#
0%
0(
b0000 *
#997
0#
#998
1#
1%
b01101100 &
b11001001 )
b0001 *
#999
0#
#1000
1#
b10010010 )
b0010 *
#1001
0#
#1002
1#
b00100100 )
b0011 *
#1003
0#
#1004
1#
b01001001 )
b0100 *
#1005
0#
#1006
1#
b01001001 '
1(
b10010011 )
b0101 *
#1007
0#
